{"cp": {"provincia": "AVILA", "fn": "19790426", "sexo": "H"}, "denunciante": {"sexo": "H", "fn": "25/02/1968", "provincia": "Argelia", "pais": "Argelia"}, "denuncia": "-- Que denuncia los hechos, que se detallan a continuacion, ocurridos a las TIEM<<<<<<<<<, del dia TIEM<<<<<<, en Aparcamiento, LOC<<<<<<<<<<<<<<<<<<<<<<<<<<<<<<<<<<<<<<<<<<<<<<<<<<<<<<<<<<<<<<<<<< . -- Que en la fecha y sobre la hora indicada, el deponente se encontraba en el lugar referido ya que habia quedado con un amigo. -- Que manifiesta haber recibido una llamada del amigo con el que habia quedado, manifestando que ha sacado su tel\u00e9fono del bolsillo, escuchando instantes despu\u00e9s el frenazo de una moto muy cerca de \u00e9l, motivo por el que ha mirado para ver qu\u00e9 habia sucedido. -- Que su amigo le indicaba en la llamada que le esperaba en otra zona de dicho centro comercial por lo que se ha dirigido al lugar. -- Que una vez con su amigo, se ha percatado que la no portaba su cartera, motivo por el que ha pensado que se le ha podido caer cuando ha sacado el tel\u00e9fono, por lo que ha regresado a ese lugar no viendo nada. -- Que esto se lo ha comentado a los vigilantes de seguridad, los cuales han podido visionar las camaras donde le indican que se le ha caido la cartera y un chico en moto, acompafiado de una chica, han frenado para coger la cartera del declarante y marcharse del lugar, indicandole que podia verse la matricula de dicha moto, si bien le informan que ha de interponer la pertinente denuncia para poder ensefar las grabaciones a la policia, siendo por esto por lo que se persona en estas dependencias. -- Que no puede aportar mas datos de lo sucedido. DIRECCION GENERAL DE LA POLICIA St MINISTERIO . iis DEL INTERIOR POLICIA NACIONAL 5 AT<<<<<<<<<<<<<<< -- "}