{"cp": {"provincia": "MADRID", "fn": "19750727", "sexo": "H"}, "denunciante": {"sexo": "M", "fn": "21/07/2002", "provincia": "Alicante", "pais": "Espana"}, "denuncia": "-- Que denuncia los hechos, que se detallan a continuaci6n, ocurridos a las TIEM<<<<<<<<<, del dia TIEM<<<<<<, en Discoteca, LOC<<<<<<<<<<<<<<<<<<<<<<<<<<<<<<<<<<<<<<<<<<<<<<<<<<<<< . --Que persona/s desconocida/s le han sustraido del interior de su bolso la cartera con los efectos abajo resefiados. --Que se percat\u00e9 de lo ocurrido porque se encontr\u00e9 el bolso abierto cuando previo a los hechos lo tenia cerrado. --Que entre los efectos habia dos tarjetas bancarias si bien le han realizado en una de ellas 1 movimientos fraudulentos por la cantidad total de 171 euros, adjuntando copia movimientos fraudulentos. --Que la tarjeta donde le han realizado los movimientos es de la entidad magic bank de caixa bank, siendo esta banca online, siendo el numero de cuenta ENUM<<<<<<<<UM<<<<<<<019, a esta cuenta esta asociada otra tarjeta de la misma entidad pero en este momento no sabe decir que numero de tarjeta es en la que le han realizado los movimientos fraudulentos. --Que el concepto de estos importes se han realizado en: \"SUQUIA PUERTO, LA MADRILENA, MONCLOA BEACH CLUB, CITY MARKET, LOC<<<<<<<<<<<<, todos en la fecha TIEM<<<<<<. --RELACION EFECTOS SUSTRAIDOS: -Una cartera de piel color estampado de vaca de pull and bear conteniendo su dni abajo resefiado, permiso conducir, dos tarjetas bancarias resefiadas, tarjeta sip, tarjeta universidad UMH, quince euros y documentacion de su animal \"perro\". DIRECCION GENERAL DE LA POLICIA St MINISTERIO iis DEL INTERIOR POLICIA NACIONAL 5 Atestado: 21/23 -- "}