{"cp": {"provincia": "GRANADA", "fn": "19781010", "sexo": "H"}, "denunciante": {"sexo": "H", "fn": "10/08/1979", "provincia": "Venezuela", "pais": "Venezuela"}, "denuncia": "-- Que denuncia los hechos, que se detallan a continuaci6n, ocurridos a las TIEM<<<<<<<<<, del dia TIEM<<<<<<, en Via publica urbana, LOC<<<<<<<<<<<<<<<<<<<<<<<<<<<<<<<<<<<<< Que a la hora, dia y lugar indicado el dicente fue requerido por dos personas, de los cuales puede aportar que eran dos varones jovenes, de tez morena, delgados, de 180 cm de estatura, vistiendo gorra y bragas que le tapaban la cara, no pudiendo aportar mas datos descriptivos. -- Que cuando el dicente se acerc\u00e9 a estos jovenes uno de ellos le empujo contra la pared del edificio y el otro le mostrd en ese momento un cuchillo grande. -- Que los autores le pidieron que le entregara todo lo que PER<<<<, haciendo el dicente entrega a los autores de un bolso que portaba, con los objetos que abajo se resefian, en su interior. -- Que tras los hechos los autores se dieron a la fuga a pie en direccion a la LOC<<<<<<<<<<<<<<<<< Que manifiesta que los autores tenian acento extranjero, como acento africano. -- Que desconcoe si en el lugar existen camaras de seguridad que pudiran haber grabado lo ocurrido. -- "}