{"cp": {"provincia": "MADRID", "fn": "19781209", "sexo": "H"}, "denunciante": {"sexo": "H", "fn": "26/05/1979", "provincia": "Don", "pais": "Espana"}, "denuncia": "-- Que denuncia los hechos, que se detallan a continuacion, ocurridos el dia TIEM<<<<<<, en Nave industrial, LOC<<<<<<<<<<<<<<<<<<<<<<<<<<<<<<<<<<<<<<<<<<. --Que se persona libre y voluntariamente ante esta instruccion para denunciar los siguientes hechos. --Que el dia de la fecha se persona en el terreno rural de su propiedad sito en el lugar indicado, comprobando que le faltan los efectos de su propiedad que se relacionan que tenia depositada en dicho terreno, sin medida de seguridad alguna. --Que carece de seguro alguno que cubra \u00e9ste tipo de hechos. -- "}