{
    "data": [
        {
            "tweet_id": "1626551491732406273",
            "text": "Nuestra semana acaba asi... \ud83d\ude0d\n\nEn los ultimos dias, entre otras cosas, hemos iniciado el proyecto de Ed.Sexual con el alumnado de 2\u00b0, 4\u00b0 de ESO y 1\u00b0 de bachillerato del @IESBClavijo. Nueve grupos increibles, cargados de reflexiones tan interesantes... \ud83d\udc9a https://t.co/9hdoXFVh3t",
            "created_at": "2023-02-17T11:57:50.000Z",
            "user_id": "1155310946",
            "username": "SeriseSexologia"
        },
        {
            "tweet_id": "1625476127018844161",
            "text": "Nuestro San Valentin \ud83e\udd79. No son flores, ni bombones... Son el mejor regalo que nos hacen este y todos los dias. Las palabras y mensajes de agradecimiento llenos de amor que nos escribe el alumnado de 4\u00b0 y 5\u00b0 de primaria del CEIP El Arco \u2763\ufe0f\n\n\u00a1Feliz Dia Europeo de la Salud Sexual! https://t.co/K6XHVMprT0",
            "created_at": "2023-02-14T12:44:43.000Z",
            "user_id": "1155310946",
            "username": "SeriseSexologia"
        },
        {
            "tweet_id": "1621418097121923073",
            "text": "Nos encanta hacer las sesiones para familias juntas pero hemos empezado a dividirnos para llegar a mas familias dada la alta demanda. Ayer, con las familias del CEIP El Arco y Caballero de la Rosa. Gracias a los centros y sus AMPAs por seguir facilitar tanto nuestro trabajo \ud83d\udc9a https://t.co/OpAvLcy1tj",
            "created_at": "2023-02-03T07:59:33.000Z",
            "user_id": "1155310946",
            "username": "SeriseSexologia"
        },
        {
            "tweet_id": "1620803009579204608",
            "text": "Para que luego digan que \"no les interesan estos temas\"... Aha... \ud83e\udd2d\ud83e\udd23 https://t.co/FHHRpmby27",
            "created_at": "2023-02-01T15:15:25.000Z",
            "user_id": "1155310946",
            "username": "SeriseSexologia"
        },
        {
            "tweet_id": "1617811746571571202",
            "text": "En una de las sesiones de 6\u00b0 de primaria de las ultimas semanas nos encontramos esta pregunta y hemos querido reflexionar sobre que idea de los cuerpos estamos transmitiendo a chicos y chicas como sociedad. \n\nhttps://t.co/nhpRvn5K4H",
            "created_at": "2023-01-24T09:09:12.000Z",
            "user_id": "1155310946",
            "username": "SeriseSexologia"
        },
        {
            "tweet_id": "1606350916260548610",
            "text": "\u00a1\u00a1FELICES FIESTAS!! https://t.co/nzjJbMKOuR",
            "created_at": "2022-12-23T18:07:57.000Z",
            "user_id": "1155310946",
            "username": "SeriseSexologia"
        },
        {
            "tweet_id": "1596128375739154433",
            "text": "\u00a1\u00a1GRACIAS!! \ud83d\udc9a https://t.co/JqcEZS6mzB",
            "created_at": "2022-11-25T13:07:14.000Z",
            "user_id": "1155310946",
            "username": "SeriseSexologia"
        },
        {
            "tweet_id": "1595735788058296321",
            "text": "Ayer nos reunimos con dos de las personas que trabajan en el @LGTBiLaRioja: Valva (Trabajadora Social) y Javi (Psicologo y Sexologo). Conocimos sus instalaciones y los recursos ofrecen. Un servicio de @lariojaorg gestionado por @gyldarioja muy necesario en nuestra comunidad \ud83c\udff3\ufe0f\u200d\ud83c\udf08 https://t.co/TYoXMkZqX6",
            "created_at": "2022-11-24T11:07:13.000Z",
            "user_id": "1155310946",
            "username": "SeriseSexologia"
        },
        {
            "tweet_id": "1593593050370084866",
            "text": "La semana que viene \u00a1MAS! (y nosotras no podemos estar mas contentas... \ud83d\udc9a) https://t.co/2RMbnxlpye",
            "created_at": "2022-11-18T13:12:45.000Z",
            "user_id": "1155310946",
            "username": "SeriseSexologia"
        },
        {
            "tweet_id": "1593184880216924161",
            "text": "Hace unas semanas os contamos que habiamos estado con Paula, directora del CEIP @villa_patro compartiendo experiencias y reflexiones en el podcast de @Rioja2 \n\nPodeis escucharlo en el siguiente enlace \ud83d\udc9a\n\nhttps://t.co/vF1SpANWvE",
            "created_at": "2022-11-17T10:10:50.000Z",
            "user_id": "1155310946",
            "username": "SeriseSexologia"
        },
        {
            "tweet_id": "1592860571099353092",
            "text": "Solo podemos decir una cosa y es que... Si o si estamos de acuerdo con este alumno \ud83d\udd1d\n\nPero que maravilla de alumnado nos encontramos en las aulas \ud83d\udc9a https://t.co/5xaEuHqiJr",
            "created_at": "2022-11-16T12:42:08.000Z",
            "user_id": "1155310946",
            "username": "SeriseSexologia"
        },
        {
            "tweet_id": "1591904657684799489",
            "text": "XII JORNADAS DE EDUCACION. SOMOS DIVERSIDAD: RE-CURSOS PARA LA REALIDAD Y LA CONVIVENCIA \ud83c\udff3\ufe0f\u200d\ud83c\udf08 Maravilla pura https://t.co/iZbEvzsadv",
            "created_at": "2022-11-13T21:23:41.000Z",
            "user_id": "1155310946",
            "username": "SeriseSexologia"
        },
        {
            "tweet_id": "1590053658506723328",
            "text": "Final del programa con 3\u00b0 de inf. del @ColeLasGaunas. Son pequenos/as en tamano pero sus reflexiones,su motivacion,su carino y su agradecimiento son...Enooormes \ud83d\udc9aEstamos deseando contar a sus familias lo que hemos trabajado \u00a1Gracias por hacernos sentir como en casa un ano mas! https://t.co/yuYXKmPf5B",
            "created_at": "2022-11-08T18:48:28.000Z",
            "user_id": "1155310946",
            "username": "SeriseSexologia"
        },
        {
            "tweet_id": "1589608677559832577",
            "text": "\u270f\ufe0f Abierto el plazo para la inscripcion al curso \"Acompanando la diversidad sexual y de genero\" que desarrollaremos las proximas semanas, promovido por el Centro Riojano de Innovacion Educativa.\n\n\u2753Mas informacion en https://t.co/wUAsxDNkfN\n\n\ud83d\udc8c Agradecemos su difusion \ud83d\udc9a https://t.co/W9oXv0bSxQ",
            "created_at": "2022-11-07T13:20:16.000Z",
            "user_id": "1155310946",
            "username": "SeriseSexologia"
        },
        {
            "tweet_id": "1588568931966812160",
            "text": "Primera semana de noviembre muy bien acompanadas... \u00a1GRACIAS! https://t.co/JqgnjbLICJ",
            "created_at": "2022-11-04T16:28:42.000Z",
            "user_id": "1155310946",
            "username": "SeriseSexologia"
        },
        {
            "tweet_id": "1585905891706130433",
            "text": "\u00a1Gracias por contar con nosotras!\n\nUn honor volver a participar en la @unirioja \ud83d\udc9a https://t.co/ife09AKdDC",
            "created_at": "2022-10-28T08:06:43.000Z",
            "user_id": "1155310946",
            "username": "SeriseSexologia"
        },
        {
            "tweet_id": "1585575608993579010",
            "text": "Esta tarde, a las 19 h, hablaremos sobre peculiaridades eroticas en las Jornadas de Psicologia Emocional (online) del Consejo de la Juventud de Logrono. Para inscribiros gratuitamente, enviad un correo a jornadaspsicologiacjlc@gmail.com \n\u00a1Os esperamos! https://t.co/KRLq8bTpSe",
            "created_at": "2022-10-27T10:14:18.000Z",
            "user_id": "1155310946",
            "username": "SeriseSexologia"
        },
        {
            "tweet_id": "1585574971639824386",
            "text": "Esta manana hemos participado junto a Paula, la directora del CEIP @villa_patro, en el podcast \"Femenino &amp; Plural\" de @Rioja2. \u00a1Un placer, como siempre, compartir tiempo e ideas con mujeres tan maravillosas! https://t.co/l4CLpU4QYC",
            "created_at": "2022-10-27T10:11:46.000Z",
            "user_id": "1155310946",
            "username": "SeriseSexologia"
        },
        {
            "tweet_id": "1584457169592016897",
            "text": "III Edicion de la Escuela UR para familias de la @unirioja https://t.co/ILS1LL2Y6I",
            "created_at": "2022-10-24T08:10:01.000Z",
            "user_id": "1155310946",
            "username": "SeriseSexologia"
        },
        {
            "tweet_id": "1583406035683139587",
            "text": "No os perdais las jornadas de Psicologia Emocional que organiza el @_CJLC_ https://t.co/QxNEpOAtXL",
            "created_at": "2022-10-21T10:33:11.000Z",
            "user_id": "1155310946",
            "username": "SeriseSexologia"
        },
        {
            "tweet_id": "1569978417650585602",
            "text": "\u00a1Que mejor manera de empezar el curso! El 29 de septiembre estaremos en la @unirioja \ud83d\udc9a\nFuturas/os docentes, os damos la bienvenida al maravilloso mundo de la Ed. Sexual en las aulas. Gracias a la UR y a la coordinadora de la jornada, Andrea Gutierrez, por contar con nosotras https://t.co/3hNhhxFzov",
            "created_at": "2022-09-14T09:16:38.000Z",
            "user_id": "1155310946",
            "username": "SeriseSexologia"
        },
        {
            "tweet_id": "1542114548039155712",
            "text": "\ud83d\udc9a\u00a1\u00a1GRACIAS POR UN CURSO MAS!!\ud83d\udc9a https://t.co/uktIBr2EG6",
            "created_at": "2022-06-29T11:55:34.000Z",
            "user_id": "1155310946",
            "username": "SeriseSexologia"
        },
        {
            "tweet_id": "1526157754997645313",
            "text": "En una de las clases en las que hemos estado esta manana del @navamudo tenian una frase que esta muy presente en nuestro trabajo.\n\n \u00bfCuantas cosas nos perdemos en el camino por centrar el foco en el destino? \n\nOjala reflexionemos sobre ello y comencemos a disfrutar del viaje. https://t.co/G8lIGJT5UR",
            "created_at": "2022-05-16T11:08:58.000Z",
            "user_id": "1155310946",
            "username": "SeriseSexologia"
        },
        {
            "tweet_id": "1525147115638366209",
            "text": "Ayer pasamos la tarde con familias de 2\u00b0,4\u00b0,5\u00b0 y 6\u00b0 de primaria del CEIP @navamudo.Agradecemos a la AMPA, centro y personas que asistieron, su participacion e interes en la sesion \"Acompanando la sexualidad de hijos/as desde las familias\".\u00a1Que ganas de conocer a vuestras joyas!\ud83d\udc9a https://t.co/ZS9kNoOQwF",
            "created_at": "2022-05-13T16:13:02.000Z",
            "user_id": "1155310946",
            "username": "SeriseSexologia"
        },
        {
            "tweet_id": "1524342766607732738",
            "text": "\u00bfQue tiene que ver Cuenca o Albacete con la Educacion de los Sexos? Compruebalo viendo el video en el que respondemos a una de las dudas mas frecuentes que nos estamos encontrando ultimamente en las aulas. https://t.co/2cSFhAYALG",
            "created_at": "2022-05-11T10:56:51.000Z",
            "user_id": "1155310946",
            "username": "SeriseSexologia"
        },
        {
            "tweet_id": "1521571754438766594",
            "text": "A ver...Fabricantes de preservativos...Poneros las pilas porque...EL PUEBLO HA HABLADO... No sabemos como lo vereis pero nosotras consideramos que hay un nicho de mercado...Quizas asi la gente se conciencie para usar proteccion en las practicas buco-genitales\ud83e\udd2d\ud83e\udd23Ahi lo dejamos... https://t.co/rmzowyMvcH",
            "created_at": "2022-05-03T19:25:50.000Z",
            "user_id": "1155310946",
            "username": "SeriseSexologia"
        },
        {
            "tweet_id": "1518951647602524160",
            "text": "Con el cuerpo cansadillo del ritmo de trabajo pero... \u00a1encantadas, oiga! https://t.co/v4UAlB1R1q",
            "created_at": "2022-04-26T13:54:28.000Z",
            "user_id": "1155310946",
            "username": "SeriseSexologia"
        },
        {
            "tweet_id": "1517550686069833733",
            "text": "\u00a1Pero que maravilla de semana! https://t.co/YiuNww289n",
            "created_at": "2022-04-22T17:07:32.000Z",
            "user_id": "1155310946",
            "username": "SeriseSexologia"
        },
        {
            "tweet_id": "1516276962096037888",
            "text": "Volvemos tras unos dias de vacaciones, desconexion y de cargar las pilas. Este es el planning de la semana \ud83d\ude05 \n\nA por el ultimo trimestre \ud83d\udcaa https://t.co/lhgWARXogU",
            "created_at": "2022-04-19T04:46:13.000Z",
            "user_id": "1155310946",
            "username": "SeriseSexologia"
        },
        {
            "tweet_id": "1512540511902617600",
            "text": "Decimos adios al trimestre con esta maravillosa ilustracion de @olgadedios  y despedimos a un alumnado increible del @CEIP7INFANTES . A la vuelta de las vacaciones nos despediremos de sus familias\nGracias por contar un ano mas con nosotras \ud83d\ude0a https://t.co/bZcMntY8FW",
            "created_at": "2022-04-08T21:18:54.000Z",
            "user_id": "1155310946",
            "username": "SeriseSexologia"
        },
        {
            "tweet_id": "1508856496339263491",
            "text": "No estais solos/as... \n\nUn abrazo fuerte autonomos/as \ud83e\udd23\ud83d\ude18 https://t.co/cHOfsPhr0f",
            "created_at": "2022-03-29T17:19:56.000Z",
            "user_id": "1155310946",
            "username": "SeriseSexologia"
        },
        {
            "tweet_id": "1507264492564066307",
            "text": "Esta semana dimos la bienvenida a la primavera en el IES Pablo Sarasate de Lodosa. Ha sido una semana increible con alumnado de 2\u00b0 ESO, PCA,PMAR, 4\u00b0 ESO y 1\u00b0 bachillerato. Ayer, reunimos a sus familias como accion final del programa de Ed.Sexual. \u00a1Gracias por contar con nosotras! https://t.co/sui6ASfIAS",
            "created_at": "2022-03-25T07:53:53.000Z",
            "user_id": "1155310946",
            "username": "SeriseSexologia"
        },
        {
            "tweet_id": "1505906371396608006",
            "text": "\u00a1\u00a1\u00a1LODOSA!!! \n\nNos vemos este viernes en la Casa de la Cultura a las 15.30.\n\nGracias al Ayuntamiento del municipio por ponerse en contacto con nosotras para el desarrollo de este tan taller \ud83d\udc9a https://t.co/y1CW97pgXv",
            "created_at": "2022-03-21T13:57:11.000Z",
            "user_id": "1155310946",
            "username": "SeriseSexologia"
        },
        {
            "tweet_id": "1504802678341357568",
            "text": "Ayer finalizamos el programa dirigido a 5\u00b0, 6\u00b0 de primaria y familias en el CEIP de Rincon de Soto. Gracias a su AMPA por contar con nosotras y al colegio por apoyar y facilitar el desarrollo de los talleres y darnos la oportunidad de pasar unos dias tan bonitos con el alumnado\ud83d\udc9a https://t.co/8GbwQo2bg3",
            "created_at": "2022-03-18T12:51:31.000Z",
            "user_id": "1155310946",
            "username": "SeriseSexologia"
        },
        {
            "tweet_id": "1503728161170808836",
            "text": "La semana pasada estuvimos en el CEIP @villa_patro. Era nuestra primera vez en este centro y \u00a1nos encanto! Familias implicadas + profesorado espectacular + alumnado muy agradecido = la combinacion perfecta que hace que sigamos enamoradas de nuestra profesion dia a dia \ud83d\udc9a https://t.co/7F9MHDFAe8",
            "created_at": "2022-03-15T13:41:46.000Z",
            "user_id": "1155310946",
            "username": "SeriseSexologia"
        },
        {
            "tweet_id": "1503727208048779271",
            "text": "@villa_patro @ampa_villapatro @educarioja \u00a1Que maravilla de centro, de alumnado, de familias y de profesorado! \ud83d\udc9a",
            "created_at": "2022-03-15T13:37:58.000Z",
            "user_id": "1155310946",
            "username": "SeriseSexologia"
        },
        {
            "tweet_id": "1498661147175702534",
            "text": "Trabajar en coles siempre es especial, pero cuando sus profesionales te reciben con los brazos abiertos,te guian x el centro para q no acabemos en el cuarto de las escobas (la orientacion no es lo nuestro \ud83e\udd2d)y te mima con un almuerzo asi...Es una maravilla!Gracias @villa_patro \ud83d\udc9a https://t.co/oC0VSY2H2I",
            "created_at": "2022-03-01T14:07:15.000Z",
            "user_id": "1155310946",
            "username": "SeriseSexologia"
        },
        {
            "tweet_id": "1498408980795830272",
            "text": "La semana pasada estuvimos en el @AytoLardero realizando la sesion previa a la intervencion con el alumnado del CEIP @villa_patro. Manana conocemos a sus joyas de 5 anos, 3\u00b0 de primaria y 6\u00b0 de primaria. \u00a1Deseando estamos! https://t.co/zcs28C7yDb",
            "created_at": "2022-02-28T21:25:14.000Z",
            "user_id": "1155310946",
            "username": "SeriseSexologia"
        },
        {
            "tweet_id": "1497262361652211716",
            "text": "Ea! Una semana mas de Educacion Sexual en centros educativos riojanos. Para captar la atencion del alumnado, tenemos que utilizar materiales llamativos,humor,diversion y en muchas ocasiones, por que no decirlo, hacer un poco de teatrillo.\nComic de \"Endometrio\" de @RocioSalgar1 \ud83d\udc9a https://t.co/GW7qBKw7fv",
            "created_at": "2022-02-25T17:28:59.000Z",
            "user_id": "1155310946",
            "username": "SeriseSexologia"
        },
        {
            "tweet_id": "1496124165966995456",
            "text": "Manana de Educacion Sexual en el @DuquesaCeip con el alumnado de 6\u00b0 de primaria. \nHay sesiones que son \"tranquilas\".\nHay otras sesiones que son... \"intensas\".\nHoy ha sido una de ellas \ud83e\udd23 \nGracias al centro y a su AMPA por contar con nosotras un ano mas \ud83d\udc9a https://t.co/an8uoaLyWH",
            "created_at": "2022-02-22T14:06:12.000Z",
            "user_id": "1155310946",
            "username": "SeriseSexologia"
        },
        {
            "tweet_id": "1494662951864659968",
            "text": "\ud83d\udc9a Desde aqui, queremos felicitar al @aytoarnedo por impulsar una actividad tan importante y necesaria. \n\n\ud83e\udec2 Estamos muy agradecidas porque hayan contado con nosotras para su puesta en marcha y por la gran acogida que ha tenido en todos los centros del municipio https://t.co/eCf9ug9gmM",
            "created_at": "2022-02-18T13:19:51.000Z",
            "user_id": "1155310946",
            "username": "SeriseSexologia"
        },
        {
            "tweet_id": "1494648390797430831",
            "text": "Hoy es un gran dia para celebrar el avance en Derechos Humanos. Gracias por tanto trabajo, esfuerzo y perseverancia de todas las personas que han conseguido que esta Ley sea una realidad en La Rioja.\n\nhttps://t.co/6kKARUGSfa",
            "created_at": "2022-02-18T12:22:00.000Z",
            "user_id": "1155310946",
            "username": "SeriseSexologia"
        },
        {
            "tweet_id": "1494643961784377345",
            "text": "LA RESISTENCIA \ud83e\udd23\ud83d\udcaa https://t.co/lRTXuPnZWV",
            "created_at": "2022-02-18T12:04:24.000Z",
            "user_id": "1155310946",
            "username": "SeriseSexologia"
        },
        {
            "tweet_id": "1492109412160446464",
            "text": "Acabamos la semana con estas palabras de 5\u00b0 del @ceip_el_arco. Dos sesiones hablando de las diferencias que nos enriquecen, de cuestiones que les generan curiosidad, de sus cuerpos y la prevencion de abusos. Un tentempie para ir abriendo boca para el ano que viene. \u00a1\u00a1GRACIAS!! https://t.co/6jBIwcfps2",
            "created_at": "2022-02-11T12:13:00.000Z",
            "user_id": "1155310946",
            "username": "SeriseSexologia"
        },
        {
            "tweet_id": "1491900004964859929",
            "text": "Hoy decimos adios al CEIP Caballero de la Rosa donde hemos cerrado el programa con una ultima sesion con familias.\nEste rincon es uno de nuestros favoritos del centro. Cuentos, una manta de ganchillo, un sofa...\ud83d\ude0d\ud83d\ude0d\ud83d\ude0d\n\nGracias un ano mas por contar con nosotras!!! https://t.co/Edp6A3B9BD",
            "created_at": "2022-02-10T22:20:54.000Z",
            "user_id": "1155310946",
            "username": "SeriseSexologia"
        },
        {
            "tweet_id": "1491778584775737346",
            "text": "\ud83d\ude0d\ud83d\ude0d tenemos la suerte de poder trabajar con joyas como este chico... https://t.co/GGxiJZJoHK",
            "created_at": "2022-02-10T14:18:25.000Z",
            "user_id": "1155310946",
            "username": "SeriseSexologia"
        },
        {
            "tweet_id": "1491494458537431045",
            "text": "Murales preciosos con mensajes importantes y necesarios que nos encontramos en los pasillos de los centros https://t.co/FiN5KAVR8R",
            "created_at": "2022-02-09T19:29:24.000Z",
            "user_id": "1155310946",
            "username": "SeriseSexologia"
        },
        {
            "tweet_id": "1490345807161311246",
            "text": "Nos sumamos a la campana de @Wanawakemujer #NoConMiFlor\nhttps://t.co/7dRv1ZUkXc https://t.co/q1Lk7JdmYe",
            "created_at": "2022-02-06T15:25:04.000Z",
            "user_id": "1155310946",
            "username": "SeriseSexologia"
        },
        {
            "tweet_id": "1485617552554434568",
            "text": "Alumnado de 6\u00b0\n\u2705 Agradecen que se les hable con naturalidad y se les proporcione un espacio donde poder expresarse y plantear sus dudas (que son muchas)\n\u2705 Agradecemos que participen, dejando a un lado las verguenzas y puedan hablar con libertad\nEn definitiva... Una maravilla \ud83d\udc9a https://t.co/J8xrxn5qF8",
            "created_at": "2022-01-24T14:16:40.000Z",
            "user_id": "1155310946",
            "username": "SeriseSexologia"
        },
        {
            "tweet_id": "1482037652094341125",
            "text": "Mas que autonomas, malabaristas del tiempo \ud83d\ude05\nPero oye, encantadas eh \ud83d\udc9a https://t.co/iSWEOhsW8W",
            "created_at": "2022-01-14T17:11:25.000Z",
            "user_id": "1155310946",
            "username": "SeriseSexologia"
        },
        {
            "tweet_id": "1476866570236403749",
            "text": "Aprendamos del pasado, vivamos el presente y construyamos el futuro. https://t.co/rpEz80Vovq",
            "created_at": "2021-12-31T10:43:23.000Z",
            "user_id": "1155310946",
            "username": "SeriseSexologia"
        },
        {
            "tweet_id": "1473981112867340293",
            "text": "\u00a1\u00a1A por la recta final del ano!!\n\u00a1\u00a1FELICES FIESTAS!! https://t.co/tMiD03FbuV",
            "created_at": "2021-12-23T11:37:37.000Z",
            "user_id": "1155310946",
            "username": "SeriseSexologia"
        },
        {
            "tweet_id": "1473288190110973961",
            "text": "Hoy ponemos fin a un trimestre...Intenso \ud83d\ude05 Pese a las \"nieblas del Ebro\",el frio de los madrugones y el ritmo frenetico, encaramos la recta final del ano con el cuerpo lleno de agradecimiento a todos los centros,AMPAs y alumnado con quien hemos tenido el lujo de compartirnos \ud83d\udc9a https://t.co/Tqrb0kWuJf",
            "created_at": "2021-12-21T13:44:11.000Z",
            "user_id": "1155310946",
            "username": "SeriseSexologia"
        },
        {
            "tweet_id": "1466093062778769411",
            "text": "Suponemos que os podeis hacer una idea de lo que significa para nosotras recibir estas reflexiones despues de una primera sesion con un grupo de 4\u00b0 de ESO. Alumnado agradecido, que valora los talleres que impartimos y tienen ganas de mas \ud83d\udc9a https://t.co/etlns4sa9i",
            "created_at": "2021-12-01T17:13:19.000Z",
            "user_id": "1155310946",
            "username": "SeriseSexologia"
        },
        {
            "tweet_id": "1463942379199737866",
            "text": "Esta manana, en uno de los centros de primaria donde hemos trabajado nos han regalado este poema de @RevolutionRoy \ud83d\udc9c\n#25N #diainternacionalcontralaviolenciadegenero #educacionsexual #logrono #larioja https://t.co/pSqdv8rjR3",
            "created_at": "2021-11-25T18:47:16.000Z",
            "user_id": "1155310946",
            "username": "SeriseSexologia"
        },
        {
            "tweet_id": "1462746998294073350",
            "text": "Inscripcion Taller Online Educacion Sexual para familias de infantil y primaria (Sabado 11 de Diciembre de 2021)\n\nHora de inicio: 11h\nDuracion: 2 horas\n\nAportacion: 20\u20ac\n\nhttps://t.co/OZXl2ELFtg https://t.co/V9nk2bB2IP",
            "created_at": "2021-11-22T11:37:15.000Z",
            "user_id": "1155310946",
            "username": "SeriseSexologia"
        },
        {
            "tweet_id": "1462034150358241286",
            "text": "Un sabado trabajando se hace menos duro cuando leemos estas maravillas... https://t.co/ljbwhzfoe9",
            "created_at": "2021-11-20T12:24:39.000Z",
            "user_id": "1155310946",
            "username": "SeriseSexologia"
        },
        {
            "tweet_id": "1461332224670933000",
            "text": "Nosotras FLIPAMOS con vuestras palabras, aportaciones y reflexiones. Cuantas cosas nos hacen falta aprender al mundo adulto de vosotras y vosotros \ud83d\udc9a https://t.co/yotodXOtpi",
            "created_at": "2021-11-18T13:55:27.000Z",
            "user_id": "1155310946",
            "username": "SeriseSexologia"
        },
        {
            "tweet_id": "1460948815805091844",
            "text": "La pre-adolescencia suele ser una etapa...intensa... Pero siempre quedan almas libres cual colibris que van fluyendo con el dia a dia \ud83d\ude02 Si es que... son adorables \ud83e\udd70 https://t.co/e3NzHE7oYX",
            "created_at": "2021-11-17T12:31:55.000Z",
            "user_id": "1155310946",
            "username": "SeriseSexologia"
        },
        {
            "tweet_id": "1460676105426329615",
            "text": "En sesiones con familias insistimos en no mentir,en contar las cosas como son adaptando el mensaje a su capacidad cognitiva. Si perciben q no es verdad lo q contamos,es posible q la siguiente pregunta q tengan busquen respuestas en lugares - fiables y - recomendables para su edad https://t.co/v16B61PWnU",
            "created_at": "2021-11-16T18:28:16.000Z",
            "user_id": "1155310946",
            "username": "SeriseSexologia"
        },
        {
            "tweet_id": "1459148557726924801",
            "text": "Retomamos las sesiones presenciales de familias que realizamos previamente a las charlas con el alumnado. \u00a1\u00a1Que ganas teniamos de volver a veros en los centros!! \ud83d\udc9a https://t.co/jROcfMbF52",
            "created_at": "2021-11-12T13:18:20.000Z",
            "user_id": "1155310946",
            "username": "SeriseSexologia"
        },
        {
            "tweet_id": "1459082882761297920",
            "text": "Solo quedan 2 plazas para cerrar el grupo de familias de infantil y primaria. Si no te has apuntado, aun estas a tiempo!!!!! https://t.co/9dIOvtwSCW",
            "created_at": "2021-11-12T08:57:22.000Z",
            "user_id": "1155310946",
            "username": "SeriseSexologia"
        },
        {
            "tweet_id": "1457763343507263491",
            "text": "Hace unas semanas realizamos 2 sesiones de formacion con usuari@s de @asprodemarioja y ARPA, asociaciones pertenecientes a @PLENALARIOJA. Gracias por contar con nosotras para compartir un espacio donde surgieron reflexiones muy enriquecedoras y donde el aprendizaje fue mutuo \ud83d\udc9a https://t.co/3vvhWlWjrC",
            "created_at": "2021-11-08T17:33:59.000Z",
            "user_id": "1155310946",
            "username": "SeriseSexologia"
        },
        {
            "tweet_id": "1455883979702276098",
            "text": "Os esperamos desde el jueves en las Jornadas de Psicologia Emocional, donde un ano mas participamos gracias al @_CJLC_ https://t.co/ya7d6sj1q0",
            "created_at": "2021-11-03T13:06:04.000Z",
            "user_id": "1155310946",
            "username": "SeriseSexologia"
        },
        {
            "tweet_id": "1446427451362582528",
            "text": "Solo quedan 6 plazas para que salga el taller de #educacionsexual en turno de manana para familias de infantil y 1er ciclo de primaria. Aun estas a tiempo de apuntarte!!\nEn turno de tarde quedan 7 plazas y\nsigue abierto  plazo para familias de 2 ciclo de primaria y de secundaria https://t.co/9dIOvtwSCW",
            "created_at": "2021-10-08T10:49:12.000Z",
            "user_id": "1155310946",
            "username": "SeriseSexologia"
        },
        {
            "tweet_id": "1438084765144453121",
            "text": "Ahora si, ahora no... Los entresijos de las relaciones con hombres/mujeres tragaperras... \u00bfsabes en que consisten? Te lo contamos en nuestro blog\n\nhttps://t.co/5UibACmVVe",
            "created_at": "2021-09-15T10:18:20.000Z",
            "user_id": "1155310946",
            "username": "SeriseSexologia"
        },
        {
            "tweet_id": "1437365591518728194",
            "text": "La creacion de escenarios en nuestra cabeza (que con frecuencia no se ajustan a la realidad) influye en la manera de vivir y gestionar las situaciones\n\nTexto de Diario de Reflexion https://t.co/SESqp8SnMF",
            "created_at": "2021-09-13T10:40:36.000Z",
            "user_id": "1155310946",
            "username": "SeriseSexologia"
        },
        {
            "tweet_id": "1436378771964284929",
            "text": "\u00bfOs imaginais a las mozas diciendoles a sus Manolos... \"Esta noche o me traes un pavo relleno que tarde 20 minutos en comermelo o no f*llas\"? \n\nEl reino animal... Curioso de narices...\n\n\ud83d\udcd6 Libro: \"La evolucion del deseo\"\n\u270f\ufe0f Autor: David M. Buss\n#animal #Origenes #humor #MIEDO https://t.co/IRJezlIRSp",
            "created_at": "2021-09-10T17:19:20.000Z",
            "user_id": "1155310946",
            "username": "SeriseSexologia"
        },
        {
            "tweet_id": "1436271729689735169",
            "text": "Taller de Educacion Sexual Online dirigido a familias\nReserva tu plaza\nhttps://t.co/gRK3M7lFpC",
            "created_at": "2021-09-10T10:13:59.000Z",
            "user_id": "1155310946",
            "username": "SeriseSexologia"
        },
        {
            "tweet_id": "1436271358992863234",
            "text": "Heroes que lloran y estan hartos de pelear: cuentos para construir otras masculinidades desde la infancia\nhttps://t.co/TSLTGjNFdN\n\n#educacion #Emociones #otromundoesposible #sexualidad",
            "created_at": "2021-09-10T10:12:31.000Z",
            "user_id": "1155310946",
            "username": "SeriseSexologia"
        },
        {
            "tweet_id": "1436270483213889536",
            "text": "#quenofalte \nEl amor se riega..... Todos los dias\n#cuidados #amor #pareja #autocuidados #sexualidad https://t.co/XooQcnVkRy",
            "created_at": "2021-09-10T10:09:02.000Z",
            "user_id": "1155310946",
            "username": "SeriseSexologia"
        },
        {
            "tweet_id": "1435888265073250305",
            "text": "Curso 2021-2022\nPreinscripcion Taller Online Educacion Sexual para familias\n\nhttps://t.co/uXKYqmFsiu",
            "created_at": "2021-09-09T08:50:14.000Z",
            "user_id": "1155310946",
            "username": "SeriseSexologia"
        },
        {
            "tweet_id": "1435286749194776576",
            "text": "Que no sea muy frecuente no significa que no exista. Por eso, todas ellas visibilizamos esta realidad.\n#diversidad #pelos #barba #cuerpos #sexualidad\n\nhttps://t.co/K7hEE4JubY",
            "created_at": "2021-09-07T17:00:02.000Z",
            "user_id": "1155310946",
            "username": "SeriseSexologia"
        },
        {
            "tweet_id": "1435163978854973440",
            "text": "Si tu AMPA o centro no estan interesados pero tu si, escribenos para hacer grupo y te avisaremos cuando lo vayamos a realizar.",
            "created_at": "2021-09-07T08:52:11.000Z",
            "user_id": "1155310946",
            "username": "SeriseSexologia"
        },
        {
            "tweet_id": "1435163909850288130",
            "text": "Abrimos hilo\n\nRecordamos que este curso mantenemos el taller Online de Educacion sexual para familias abierto a todo el territorio nacional. Si quieres mas informacion contactanos:\n628025052\ninfo@serisesexologia.com\n\n... https://t.co/NYLWRNWCO9",
            "created_at": "2021-09-07T08:51:54.000Z",
            "user_id": "1155310946",
            "username": "SeriseSexologia"
        },
        {
            "tweet_id": "1434939458579681282",
            "text": "\"La vejez no esta renida con el deseo sexual. El deseo nos mantiene vivos, activos y sanos\" Ivan Rotella en https://t.co/RuTqykdSp8  habla sobre ello.",
            "created_at": "2021-09-06T18:00:01.000Z",
            "user_id": "1155310946",
            "username": "SeriseSexologia"
        },
        {
            "tweet_id": "1434820025739878402",
            "text": "Ya estamos de vuelta inagurando el curso 2021-2022.Este ano mantendremos la modalidad online como opcional en las formaciones a familias. Si perteneces a una AMPA y quieres que vayamos a vuestro centro os recordamos las vias de contacto:\n\u260e\ufe0f 628025052  \n\ud83d\udce7 info@serisesexologia.com https://t.co/lwAJnehD7I",
            "created_at": "2021-09-06T10:05:26.000Z",
            "user_id": "1155310946",
            "username": "SeriseSexologia"
        },
        {
            "tweet_id": "1434816084679565321",
            "text": "Pues eso, que recuerdes.... Sea como sea tu cuerpo... es bello\n#cuerposquemolan  #cuerposreales  #amatucuerpo #diversidadcorporal https://t.co/dtaPQNa7Xs",
            "created_at": "2021-09-06T09:49:46.000Z",
            "user_id": "1155310946",
            "username": "SeriseSexologia"
        },
        {
            "tweet_id": "1433013013175422982",
            "text": "Acaba de publicar una foto https://t.co/rxHvSEOvHI",
            "created_at": "2021-09-01T10:25:01.000Z",
            "user_id": "1155310946",
            "username": "SeriseSexologia"
        },
        {
            "tweet_id": "1415343722083016704",
            "text": "Nuestra experiencia en las aulas ante el auge de influencers como fuente de informacion sobre sexualidad en @Rioja2\n\nhttps://t.co/mREBqWHlc8",
            "created_at": "2021-07-14T16:13:33.000Z",
            "user_id": "1155310946",
            "username": "SeriseSexologia"
        },
        {
            "tweet_id": "1407636377009856514",
            "text": "Para reflexionar un poquito sobre esos discursos que dicen que el alumnado no tiene interes en la educacion sexual. \n\nSpoiler: LO TIENE. Y si no encuentra respuestas en la familia o en el centro educativo, acabara buscandola en otras vias menos adaptadas para su edad. https://t.co/5op5j8iMMz",
            "created_at": "2021-06-23T09:47:19.000Z",
            "user_id": "1155310946",
            "username": "SeriseSexologia"
        },
        {
            "tweet_id": "1406165971203760132",
            "text": "Esta semana nos hemos dividido entre el CEIP Antonio Delgado Calvete (Arnedo) y el CEO Villa de Autol. Mas de 110 alumnos/as han recibido nuestras charlas \ud83e\udd70 \n\nGracias a AMPAs y centros por confiar un ano mas en nosotras y por facilitar las cosas en un ano tan dificil... https://t.co/oa2JToT2xa",
            "created_at": "2021-06-19T08:24:27.000Z",
            "user_id": "1155310946",
            "username": "SeriseSexologia"
        },
        {
            "tweet_id": "1404402907613650946",
            "text": "Esta semana hemos colaborado con @eldiarioes para reflexionar un poquito sobre la Educacion Sexual. \u00a1Gracias @martaborraz por contar con nosotras!\n\nhttps://t.co/sxtpvAG5Kv",
            "created_at": "2021-06-14T11:38:40.000Z",
            "user_id": "1155310946",
            "username": "SeriseSexologia"
        },
        {
            "tweet_id": "1402536515029307392",
            "text": "Nos cogemos unos dias de merecido descanso para poder encarar la recta final del curso 2020-2021. Volvemos el lunes 14 \ud83d\ude0a\n\n\u00a1\u00a1Feliz dia de La Rioja!! https://t.co/XR0qouY3fp",
            "created_at": "2021-06-09T08:02:17.000Z",
            "user_id": "1155310946",
            "username": "SeriseSexologia"
        },
        {
            "tweet_id": "1395351466924249092",
            "text": "Un ano mas en el @CEIP_El_Arco \ud83d\ude0d \nUnos grupos de 6\u00b0 de primaria muy participativos, aunque ya teniamos la suerte de conocerles porque el ano pasado tambien realizamos sesiones en 5\u00b0. Gracias tanto al centro como a la AMPA. \u00a1\u00a1Siempre es un placer estar en vuestro centro!! https://t.co/DI4sDtmoXp",
            "created_at": "2021-05-20T12:11:28.000Z",
            "user_id": "1155310946",
            "username": "SeriseSexologia"
        },
        {
            "tweet_id": "1392059187421659138",
            "text": "\u00a1\u00a1Una maravilla de grupos!! \ud83d\ude0d",
            "created_at": "2021-05-11T10:09:08.000Z",
            "user_id": "1155310946",
            "username": "SeriseSexologia"
        },
        {
            "tweet_id": "1392059185274183681",
            "text": "Un alumnado, q por sus reflexiones finales, nos dice q se ha quedado con ganas de mas sesiones, senalando q nuestras charlas son distintas a otras q han recibido y agradeciendo q nos hayamos centrado en los temas q realmente les interesan de una manera cercana, directa y natural.",
            "created_at": "2021-05-11T10:09:07.000Z",
            "user_id": "1155310946",
            "username": "SeriseSexologia"
        },
        {
            "tweet_id": "1392059183051255808",
            "text": "Con el trajin de semana que llevamos, se nos habia olvidado contaros que durante las ultimas dos semanas hemos estado con los grupos de 4\u00b0 de ESO del @iesedaniel https://t.co/s5hMsOwy0I",
            "created_at": "2021-05-11T10:09:07.000Z",
            "user_id": "1155310946",
            "username": "SeriseSexologia"
        },
        {
            "tweet_id": "1391726939401072640",
            "text": "@JUANINLLO Animo companero!! Cuidate mucho!! Te mandamos un abrazo fuerte!!",
            "created_at": "2021-05-10T12:08:54.000Z",
            "user_id": "1155310946",
            "username": "SeriseSexologia"
        },
        {
            "tweet_id": "1385228252172754949",
            "text": "\"La diversidad nos enriquece y el respeto une\".Con esta frase tan acorde a nuestras charlas, concluimos el programa de Ed.Sexual de 6\u00b0en el @ColeLasGaunas.Ya son 7 anos y siempre acabamos con una sensacion muy especial. Un alumnado,familias,profesorado y AMPA increibles. Gracias! https://t.co/J2xJom5uIk",
            "created_at": "2021-04-22T13:45:26.000Z",
            "user_id": "1155310946",
            "username": "SeriseSexologia"
        },
        {
            "tweet_id": "1384489555361947650",
            "text": "\u00a1Ea! Pues ya estaria... Jajajajaja\n\n#RuralStyle #regla #menstruacion #sexualidad #sexologia #EducacionSexual https://t.co/cwML8bRH6e",
            "created_at": "2021-04-20T12:50:07.000Z",
            "user_id": "1155310946",
            "username": "SeriseSexologia"
        },
        {
            "tweet_id": "1384215358941196292",
            "text": "Comienzo de semana intenso \u263a\ufe0f \n\n\ud83d\udc69\ud83c\udffb\u200d\ud83c\udfeb Por la manana, sesiones presenciales con tres grupos de 6\u00b0 de primaria en un cole. \n\n\ud83d\udcbbPor la tarde, sesiones virtuales de cierre de familias del @DuquesaCeip y CEIP Nuestra Senora de la Vega (Haro). https://t.co/TkRkBZtJLY",
            "created_at": "2021-04-19T18:40:33.000Z",
            "user_id": "1155310946",
            "username": "SeriseSexologia"
        },
        {
            "tweet_id": "1383485217759907842",
            "text": "Esta semana nos hemos trasladado a la Rioja Alta,al CEIP Nuestra Senora de la Vega(Haro).Hemos tenido la suerte de conocer a un grupo de 6\u00b0 encantador. Gracias a ellas/os por compartir sus reflexiones,intereses y dudas con nosotras,al centro y a su AMPA por contar con nosotras \ud83e\udd70 https://t.co/0RO1mKi2f9",
            "created_at": "2021-04-17T18:19:14.000Z",
            "user_id": "1155310946",
            "username": "SeriseSexologia"
        },
        {
            "tweet_id": "1379701334375550977",
            "text": "Gracias a @Rioja2 por contar con @SeriseSexologia en este espacio de reflexion sobre la coeducacion en las aulas. Es un placer compartir video con grandes mujeres \nhttps://t.co/uOMnZh3BDJ\n@FAPARioja @ampa_villapatro @iesedaniel",
            "created_at": "2021-04-07T07:43:26.000Z",
            "user_id": "1155310946",
            "username": "SeriseSexologia"
        },
        {
            "tweet_id": "1379412859587866625",
            "text": "Aprovechamos estos dias para contaros que hemos hecho las ultimas semanas.Tuvimos la suerte de estar en el CEIP Eduardo Gonzalez Gallarza de Rincon de Soto con el alumnado de 5\u00b0 y 6\u00b0. Era la 1\u00aa vez y la acogida no pudo ser mejor \ud83d\udc9a Gracias al centro y AMPA por contar con nosotras https://t.co/0IzbwY97px",
            "created_at": "2021-04-06T12:37:08.000Z",
            "user_id": "1155310946",
            "username": "SeriseSexologia"
        },
        {
            "tweet_id": "1378264017240743936",
            "text": "El pasado lunes estuvimos en el @ateneo_riojano rodeadas de un publico participativo y reflexivo tras nuestra charla, \"Pornografia: \u00bfLa nueva educacion sexual?\"\nEchabamos muchisimo de menos hacer actividades abiertas al publico de manera presencial, asi que fue un gustazo \ud83e\udd70 https://t.co/i8s7otEKnN",
            "created_at": "2021-04-03T08:32:03.000Z",
            "user_id": "1155310946",
            "username": "SeriseSexologia"
        },
        {
            "tweet_id": "1377979373152837634",
            "text": "Los medios de comunicacion y la informacion no entienden de festivos...hoy, hemos estado en @RadioRioja hablando de pornografia. Gracias por la invitacion!! Podeis escucharnos a partir del minuto 22 \ud83d\udc9a\n\nhttps://t.co/Bcc3RqN1Gm https://t.co/xNpXW4x3VO",
            "created_at": "2021-04-02T13:40:58.000Z",
            "user_id": "1155310946",
            "username": "SeriseSexologia"
        },
        {
            "tweet_id": "1377683645935276032",
            "text": "Todo un lujo!! Unos grupos estupendos y un profesorado y AMPA de 10!! Gracias!! https://t.co/fNov1RWDOq",
            "created_at": "2021-04-01T18:05:51.000Z",
            "user_id": "1155310946",
            "username": "SeriseSexologia"
        },
        {
            "tweet_id": "1377316816628879366",
            "text": "Si realmente quereis saber por que es necesario un dia como hoy, leed... Leed mucho e informaros\n\n#DiaInternacionalDeLaVisibilidadTrans #31marzo https://t.co/CzWOylv6jm",
            "created_at": "2021-03-31T17:48:13.000Z",
            "user_id": "1155310946",
            "username": "SeriseSexologia"
        },
        {
            "tweet_id": "1375395254149480449",
            "text": "\ud83d\udcddLUNES, 29 de marzo, en Ateneo Riojano \n\ud83d\udd62 19:30 \n\ud83d\udccd Muro de Cervantes 1, 1\u00b0\n\u2b50Acceso gratuito\u2b50\n\ud83d\ude37 Protocolos de seguridad garantizados\n\nGracias al @ateneo_riojano  por contar con nosotras, al @AytoLogrono y @lariojaorg por su colaboracion. https://t.co/x70QRkaKJz",
            "created_at": "2021-03-26T10:32:36.000Z",
            "user_id": "1155310946",
            "username": "SeriseSexologia"
        }
    ]
}