{
    "data": [
        {
            "tweet_id": "1627421595668029440",
            "text": "@nachovalles_14 @bmSinfin @Herrerolon Grande nacho,  tu si que sabes!!! \ud83d\ude09",
            "created_at": "2023-02-19T21:35:19.000Z",
            "user_id": "604530801",
            "username": "vicentenieto8"
        },
        {
            "tweet_id": "1627411485159743491",
            "text": "Sin palabras...  sufrimiento,  pasion y minutos finales de infarto @bmSinfin \nGracias equipo,  gracias aficion, vibro la albericia\n#Santander #Cantabria \ud83d\udda4 https://t.co/BbSaIXKWyc",
            "created_at": "2023-02-19T20:55:08.000Z",
            "user_id": "604530801",
            "username": "vicentenieto8"
        },
        {
            "tweet_id": "1627059536497610754",
            "text": "Animo @bmpereda ejemplo pese a la derrota de sacrificio y entrega.  Manana seguro sale el \ud83c\udf1e \nSeguiremos creyendo en este firme proyecto \ud83e\udd3e\u200d\u2640\ufe0f\nBuen viaje de regreso @RodriguezCleba \n#Santander #Cantabria https://t.co/YViGJifNMo",
            "created_at": "2023-02-18T21:36:37.000Z",
            "user_id": "604530801",
            "username": "vicentenieto8"
        },
        {
            "tweet_id": "1624704646446034946",
            "text": "@jrrcsdr @bmSinfin @pedrolopez8a Muchas gracias por tu aportacion \ud83d\udc4f\ud83d\udc4f",
            "created_at": "2023-02-12T09:39:07.000Z",
            "user_id": "604530801",
            "username": "vicentenieto8"
        },
        {
            "tweet_id": "1624490913786363904",
            "text": "Soberbia segunda parte, fundamental victoria \ud83d\udda4\n@bmSinfin y capitulo aparte la porteria. Dios esta bajo los palos!!! \n#aupasinfin https://t.co/AbcavQGbuS",
            "created_at": "2023-02-11T19:29:50.000Z",
            "user_id": "604530801",
            "username": "vicentenieto8"
        },
        {
            "tweet_id": "1622307272574517250",
            "text": "@JUANJO414 @bmSinfin @Garabaya @CdadLogrono Pues ni puta gracia, campeon",
            "created_at": "2023-02-05T18:52:49.000Z",
            "user_id": "604530801",
            "username": "vicentenieto8"
        },
        {
            "tweet_id": "1622288363238707202",
            "text": "@JUANJO414 @bmSinfin @Garabaya @CdadLogrono Noooo que va!te enseno\nA tu disposicion lo que me cuesta vivir el deporte, apasionado de ello, sentirlo y vivirlo para mi cuidad, ademas de buscar patrocinadores e incluso despedir a un deportista.\nTe dejo que estoy en un funeral de uno de ellos,aqui no me piden ser socio/abonado",
            "created_at": "2023-02-05T17:37:41.000Z",
            "user_id": "604530801",
            "username": "vicentenieto8"
        },
        {
            "tweet_id": "1622228122832670720",
            "text": "Espectacular @bmSinfin \nQue mejor manera de comenzar el ano y la segunda vuelta,  siempre con vosotros,  siempre #sinfin\nAnimo @Garabaya tu seras la luz que nos guie \ud83d\ude09\ud83c\udfb6\ud83c\udfb5\nBuen viaje de regreso @CdadLogrono\n#Cantabria #sinfin \ud83c\uddf5\ud83c\uddf1\ud83d\udda4 https://t.co/ZrApKiQR2X",
            "created_at": "2023-02-05T13:38:18.000Z",
            "user_id": "604530801",
            "username": "vicentenieto8"
        },
        {
            "tweet_id": "1618748108321726467",
            "text": "@potamitorrc Un mierdas aprendiz de valiente",
            "created_at": "2023-01-26T23:09:58.000Z",
            "user_id": "604530801",
            "username": "vicentenieto8"
        },
        {
            "tweet_id": "1618327056810672129",
            "text": "Que grande el balonmano,  que grande el deporte y con tres cantabros \ud83d\udca2 como tres \ud83c\udf1e\n#handball23 #cantabria\nY #Norway como gran rival\nEnhorabuena a los vencedores y un gran rival del que solo podemos aprender\ud83c\uddea\ud83c\uddf8 https://t.co/scPQM2MZhE",
            "created_at": "2023-01-25T19:16:52.000Z",
            "user_id": "604530801",
            "username": "vicentenieto8"
        },
        {
            "tweet_id": "1614346662226591744",
            "text": "Victoria. Importante, y tres puntos..  @realracingclub pero hoy hemos demostrado lo importante que es la aficion. \nUn 10 para los nuestros @GradonaMalditos @JJVV86 @APR_Racing \ud83d\udc9a\ud83d\udcaa",
            "created_at": "2023-01-14T19:40:12.000Z",
            "user_id": "604530801",
            "username": "vicentenieto8"
        },
        {
            "tweet_id": "1610253693454106624",
            "text": "@josemaholgado Un fuerte abrazo y mucho animo",
            "created_at": "2023-01-03T12:36:12.000Z",
            "user_id": "604530801",
            "username": "vicentenieto8"
        },
        {
            "tweet_id": "1604182186734899202",
            "text": "@pelicato @gemaigual @TurismoSDR @elfaradio @dmontanes @BombSantander @ondacerocan Ahora paso aviso,  gracias Mario",
            "created_at": "2022-12-17T18:30:12.000Z",
            "user_id": "604530801",
            "username": "vicentenieto8"
        },
        {
            "tweet_id": "1598794600189239297",
            "text": "Hoy mas que nunca @bmSinfin\ud83d\udda4\nQue facil es ser de los ganadores y de los que apuestan por ello desde los diferentes estamentos. \nOjala lleguen tiempos mejores, tiempos en los que el deporte sea eso,un reflejo,un modo de vida de una ciudad que vive como nadie el deporte\ud83d\udcaa",
            "created_at": "2022-12-02T21:41:51.000Z",
            "user_id": "604530801",
            "username": "vicentenieto8"
        },
        {
            "tweet_id": "1593328468804116483",
            "text": "Celebremoslo @APR_Racing @JJVV86 @GradonaMalditos con pancartas, megafono y bombos asi se vera mejor, con nueva luz, que..... #AnimarNoEsDelito \n#auparacing \ud83d\udc9a https://t.co/V71bGR0Lzs",
            "created_at": "2022-11-17T19:41:24.000Z",
            "user_id": "604530801",
            "username": "vicentenieto8"
        },
        {
            "tweet_id": "1592631951407845376",
            "text": "\"La mejor manera de saber si puedes confiar en alguien es confiando\"\n(Ernest Hemingway)\nHoy mas que nunca,  siempre @bmSinfin\n\ud83d\udcaa\ud83d\udda4\ud83c\uddf5\ud83c\uddf1",
            "created_at": "2022-11-15T21:33:41.000Z",
            "user_id": "604530801",
            "username": "vicentenieto8"
        },
        {
            "tweet_id": "1586403502460260353",
            "text": "Fantastico punto el conseguido en Huesca @bmSinfin \nSeguimos y seguiremos creyendo en este maravilloso grupo humano dirigido por @Garabaya \ud83d\udcaa\ud83d\udda4\n#aupasinfin https://t.co/h7nWgogU1L",
            "created_at": "2022-10-29T17:04:03.000Z",
            "user_id": "604530801",
            "username": "vicentenieto8"
        },
        {
            "tweet_id": "1583708832269680641",
            "text": "No hace falta conocer mucho a una persona para pronto hacerla un hueco en tu vida. \n#yeyocampos regalaba alegria, consejos, pasion, respeto y sobre todo,  mucho, mucho carino. \nBuen viaje amigo, vuelta alto \ud83d\udc94 https://t.co/lq5F9hlJbS",
            "created_at": "2022-10-22T06:36:24.000Z",
            "user_id": "604530801",
            "username": "vicentenieto8"
        },
        {
            "tweet_id": "1581356888683270144",
            "text": "\ud83d\udcaa\ud83d\udcaa\ud83d\udcaaseguimos haciendo camino!! \ud83d\udc9a https://t.co/rgWt0QeAba",
            "created_at": "2022-10-15T18:50:37.000Z",
            "user_id": "604530801",
            "username": "vicentenieto8"
        },
        {
            "tweet_id": "1581188947790954496",
            "text": "@jrrcsdr No no,  dos cosas diferentes. Lo que comente ayer es la renovacion del cesped del ya existente debido a su mal estado como tambien se hara en el del regimiento. \nUn saludo \ud83d\udc9a",
            "created_at": "2022-10-15T07:43:16.000Z",
            "user_id": "604530801",
            "username": "vicentenieto8"
        },
        {
            "tweet_id": "1578472217398358017",
            "text": "Buen viaje de regreso #guerreros",
            "created_at": "2022-10-07T19:47:57.000Z",
            "user_id": "604530801",
            "username": "vicentenieto8"
        },
        {
            "tweet_id": "1578468137645010945",
            "text": "Derrotas que saben a victorias, viajes imposibles que se compiten, tristezas que se convierten en ilusiones @Garabaya \nEste a arbol dara sus frutos\nSeguimos y seguiremos sonando @bmSinfin \ud83d\udcaa\ud83d\udda4\n#aupasinfin https://t.co/hLYEOlqe1p",
            "created_at": "2022-10-07T19:31:45.000Z",
            "user_id": "604530801",
            "username": "vicentenieto8"
        },
        {
            "tweet_id": "1578427951393038338",
            "text": "@PabloPuente17 @uneatlantico Enhorabuena, recompensa al esfuerzo!",
            "created_at": "2022-10-07T16:52:04.000Z",
            "user_id": "604530801",
            "username": "vicentenieto8"
        },
        {
            "tweet_id": "1574107225991299072",
            "text": "Espero que esteis todos bien,  el resultado,  lo de menos.\n Se confundieron de enemigo, solo se iba a animar y apoyar.  Estamos locos, confundimos seguidores y animadores con delincuencia\n\u274c\ufe0f error @SDEibar https://t.co/bWBAFgWudN",
            "created_at": "2022-09-25T18:43:02.000Z",
            "user_id": "604530801",
            "username": "vicentenieto8"
        },
        {
            "tweet_id": "1573624129470734337",
            "text": "@santandersucio @bmSinfin @Garabaya @raulhuerta81 @vandorevuelta @BertoPla_7 @1991DMG @Herrerolon Solicitadas mas de 130 actuaciones en barrios durante estos tres anos en la comision de desarrollo para que intervenga el equipo de gobierno. Pero seguro aun quedan mas! Y con la dificultad de no tener dedicacion exclusiva y trabajar mas de ocho horas diarias.Gracias por exigirme",
            "created_at": "2022-09-24T10:43:23.000Z",
            "user_id": "604530801",
            "username": "vicentenieto8"
        },
        {
            "tweet_id": "1573428010451181568",
            "text": "SEGUIMOS Y SEGUIREMOS SONANDO JUNTOS @bmSinfin \nSobresaliente la aficion, el equipo, la direccion @Garabaya y como decia la cancion....\n\"Sin ti, no soy nada... \ud83c\udfb6\ud83c\udfb5\ud83c\udfb6\"\n#aupasinfin https://t.co/WHyb25qZIh",
            "created_at": "2022-09-23T21:44:05.000Z",
            "user_id": "604530801",
            "username": "vicentenieto8"
        },
        {
            "tweet_id": "1571495374111612931",
            "text": "@Jjambrina79 @realracingclub @UDLP_Oficial @APR_Racing @JJVV86 @GradonaMalditos Gracias @GradonaMalditos \ud83d\udc9a\ud83d\udc9a\ud83d\udc9a\ud83d\udc9a",
            "created_at": "2022-09-18T13:44:28.000Z",
            "user_id": "604530801",
            "username": "vicentenieto8"
        },
        {
            "tweet_id": "1571493300367917056",
            "text": "Previa @realracingclub @UDLP_Oficial \nEnhorabuena @APR_Racing @JJVV86 \ud83d\udc9a https://t.co/ZRNihE8D66",
            "created_at": "2022-09-18T13:36:14.000Z",
            "user_id": "604530801",
            "username": "vicentenieto8"
        },
        {
            "tweet_id": "1568964278895493120",
            "text": "+3 a pesar de las dificultades, siempre aupa Racing!\ud83d\udc9a https://t.co/4Vc8zh4eKy",
            "created_at": "2022-09-11T14:06:48.000Z",
            "user_id": "604530801",
            "username": "vicentenieto8"
        },
        {
            "tweet_id": "1568926208930324481",
            "text": "Seguimos sonando @ASOBAL \n@bmSinfin 21-21 @AnaitasunaBM \n#aupasinfin \ud83d\udda4\ud83e\udd3e\u200d\u2642\ufe0f\ud83c\uddf5\ud83c\uddf1 https://t.co/gCEfd6KTkE",
            "created_at": "2022-09-11T11:35:32.000Z",
            "user_id": "604530801",
            "username": "vicentenieto8"
        },
        {
            "tweet_id": "1567257120688463872",
            "text": "\u27a1\ufe0f INCREIBLE!!!! @bmSinfin que inyeccion de moral y adrenalina en la primera jornada y ante un equipo con aspiraciones europeas.  \ud83d\udcaa\ud83d\udda4\ud83c\uddf5\ud83c\uddf1\ud83e\udd3e\u200d\u2642\ufe0f\nSonaremos @SERVANDOREVUELT \n#aupasinfin https://t.co/YifsTnbwPb",
            "created_at": "2022-09-06T21:03:10.000Z",
            "user_id": "604530801",
            "username": "vicentenieto8"
        },
        {
            "tweet_id": "1566064727431716867",
            "text": "Toda la ilusion, en un nuevo proyecto,  quizas el mas dificil, pero siempre @bmSinfin nos ha demostrado que lo imposible para nosotros solo es un \"poco\" mas dificil!! Gracias #blendio por el apoyo al deporte \n\ud83e\udd3e\u200d\u2642\ufe0f\ud83c\uddf5\ud83c\uddf1\ud83d\udda4\n#Santander #Cantabria #asobal #Handball #Deporte #Salud https://t.co/fV2EXcGCYs",
            "created_at": "2022-09-03T14:05:01.000Z",
            "user_id": "604530801",
            "username": "vicentenieto8"
        },
        {
            "tweet_id": "1561724021443641346",
            "text": "|---|    |---|   |---|\n|     |---|  |---|     |       \n|___               ___|\n      |             |\n      |             |    \ud83d\udd1c    \ud83d\udfe6\ud83d\udfe5 \ud83d\udeeb\ud83d\udeec\ud83d\udfe9\u2b1c\ufe0f = \ud83d\udcaa\ud83d\udc9a\u26bd\ufe0f\n      |             |\n ___|             |___          aupa @realracingclub\n|_______________|",
            "created_at": "2022-08-22T14:36:36.000Z",
            "user_id": "604530801",
            "username": "vicentenieto8"
        },
        {
            "tweet_id": "1560242418628411393",
            "text": "@Gal0nso Animo y pronta recuperacion! \ud83d\udcaa",
            "created_at": "2022-08-18T12:29:15.000Z",
            "user_id": "604530801",
            "username": "vicentenieto8"
        },
        {
            "tweet_id": "1559871045829595136",
            "text": "Mucho animo cachorro @jaimegallegom \ud83d\udcaa https://t.co/Aq8rQHTSz9",
            "created_at": "2022-08-17T11:53:32.000Z",
            "user_id": "604530801",
            "username": "vicentenieto8"
        },
        {
            "tweet_id": "1556915765294632965",
            "text": "@jrrcsdr @FelipePManso @fcf_es @RadioFutbolFCF @YEYDA @pedrolopez8a @diegobalbontin @jdelcastillog @CarlosValle_a Es una negociacion entre la concejalia de deportes y la federacion. Ojala podamos contar con nuevas instalaciones en la ciudad gracias a la @fcf_es",
            "created_at": "2022-08-09T08:10:19.000Z",
            "user_id": "604530801",
            "username": "vicentenieto8"
        },
        {
            "tweet_id": "1556915214901207042",
            "text": "@jrrcsdr Seguimos esperando a la convocatoria de una nueva reunion en la que nos tienen que informar de las propuestas a llevar a cabo.  Son muchos meses de espera....",
            "created_at": "2022-08-09T08:08:07.000Z",
            "user_id": "604530801",
            "username": "vicentenieto8"
        },
        {
            "tweet_id": "1544649580209487873",
            "text": "@AngelCosmea @realracingclub @australoficial Aupa cachorro!!! \ud83d\ude0d\ud83d\udc9a",
            "created_at": "2022-07-06T11:48:52.000Z",
            "user_id": "604530801",
            "username": "vicentenieto8"
        },
        {
            "tweet_id": "1534873458739490817",
            "text": "Si se hace bien, pues se dice, todo mi reconocimiento, asi que fantastica noticia https://t.co/kUM08Hinpf",
            "created_at": "2022-06-09T12:22:03.000Z",
            "user_id": "604530801",
            "username": "vicentenieto8"
        },
        {
            "tweet_id": "1534860323521445889",
            "text": "Por fin, estamos de enhorabuena!! \ud83d\udc9a\u26bd\ufe0f\nEl Ayuntamiento y el Racing firman un convenio de colaboracion para los proximos cuatro anos\nhttps://t.co/LYwQQOop2p",
            "created_at": "2022-06-09T11:29:52.000Z",
            "user_id": "604530801",
            "username": "vicentenieto8"
        },
        {
            "tweet_id": "1534417216409681920",
            "text": "@victormf17 @bmSinfin Muchas gracias por tu dedicacion.  Toda la suerte del mundo \ud83e\udd3e\u200d\u2642\ufe0f",
            "created_at": "2022-06-08T06:09:07.000Z",
            "user_id": "604530801",
            "username": "vicentenieto8"
        },
        {
            "tweet_id": "1533740147518459904",
            "text": "#eternopreciado\nSiempre seguira entre todos nosotros y \u26bd\ufe0f\ud83e\udec2 https://t.co/ZEdWo8lSxA",
            "created_at": "2022-06-06T09:18:41.000Z",
            "user_id": "604530801",
            "username": "vicentenieto8"
        },
        {
            "tweet_id": "1533146368549740549",
            "text": "Somos de @ASOBAL un ano mas.  Quizas lo mas destacable de la temporada\nAupa @bmSinfin \ud83d\udda4 https://t.co/2SylL4ak3P",
            "created_at": "2022-06-04T17:59:13.000Z",
            "user_id": "604530801",
            "username": "vicentenieto8"
        },
        {
            "tweet_id": "1532835271166808064",
            "text": "Campeones!!!! \ud83d\udc9a\ud83d\udc9a\ud83d\udc9a asignatura pendiente,  la liga profesional @realracingclub https://t.co/D7oVdJkBrR",
            "created_at": "2022-06-03T21:23:02.000Z",
            "user_id": "604530801",
            "username": "vicentenieto8"
        },
        {
            "tweet_id": "1532099165177643008",
            "text": "Ser o estar, estar o ser que mas da,  pero que leccion @bmSinfin lejos\nPero solo una cosa, @eonalicante gracias por vuestra acogida como anfitriones. Nos vemos en @ASOBAL\n\ud83d\udda4\ud83d\udda4\ud83e\uddbe",
            "created_at": "2022-06-01T20:38:00.000Z",
            "user_id": "604530801",
            "username": "vicentenieto8"
        },
        {
            "tweet_id": "1532087221175693314",
            "text": "@bmSinfin cada vez mas cerca!!!\n#aupasinfin \ud83d\udda4",
            "created_at": "2022-06-01T19:50:32.000Z",
            "user_id": "604530801",
            "username": "vicentenieto8"
        },
        {
            "tweet_id": "1530959674140508161",
            "text": "Seguimos vivos!!!!\nTemporada dificil,  final de infarto pero seguiremos creyendo y sonando con que @bmSinfin siga siendo de @ASOBAL \ud83e\uddbe\u2764\ufe0f\ud83d\udda4\n#aupasinfin https://t.co/Z9C4iLS2yA",
            "created_at": "2022-05-29T17:10:04.000Z",
            "user_id": "604530801",
            "username": "vicentenieto8"
        },
        {
            "tweet_id": "1529432734040473602",
            "text": "@Gal0nso Totalmente de acuerdo!",
            "created_at": "2022-05-25T12:02:33.000Z",
            "user_id": "604530801",
            "username": "vicentenieto8"
        },
        {
            "tweet_id": "1529130366195453959",
            "text": "@antonsetieen7 @BMTorrelavega @CabronesdelNort Animo cachorro! \u2764\ud83e\udd3e\u200d\u2642\ufe0f",
            "created_at": "2022-05-24T16:01:03.000Z",
            "user_id": "604530801",
            "username": "vicentenieto8"
        },
        {
            "tweet_id": "1527945353013694465",
            "text": "Y por que no creer en los milagros @bmSinfin \nCreer, creer y creer\ud83d\udc40\ud83e\uddbe\ud83d\udda4\nLo imposible con este equipo solo es un poco mas dificil \n#aupasinfin",
            "created_at": "2022-05-21T09:32:14.000Z",
            "user_id": "604530801",
            "username": "vicentenieto8"
        },
        {
            "tweet_id": "1525420527770292224",
            "text": "Gracias @FundacionCruyff gracias @FundlaCaixa \npor dotar al #barriopesquero de una instalacion muy mejorada para el uso y disfrute de todos los ninos y jovenes.  #santander #cantabria \u26bd\ufe0f\ud83c\uddf5\ud83c\uddf1 https://t.co/HMr1HUT6dj",
            "created_at": "2022-05-14T10:19:29.000Z",
            "user_id": "604530801",
            "username": "vicentenieto8"
        },
        {
            "tweet_id": "1521212199200608259",
            "text": "@AitorAlexandre @frandi1984 Grande!! Viejo!!! \ud83d\udc9a",
            "created_at": "2022-05-02T19:37:05.000Z",
            "user_id": "604530801",
            "username": "vicentenieto8"
        },
        {
            "tweet_id": "1520988256493621248",
            "text": "@korokotta75 Lo seremos!!!! \ud83d\udc9a\ud83d\udcaa y pronto!!!!",
            "created_at": "2022-05-02T04:47:13.000Z",
            "user_id": "604530801",
            "username": "vicentenieto8"
        },
        {
            "tweet_id": "1520756220507963392",
            "text": "Somos del segunda!!!\nEnhorabuena aficion \ud83d\udc9a https://t.co/xRuYzc3kjL",
            "created_at": "2022-05-01T13:25:11.000Z",
            "user_id": "604530801",
            "username": "vicentenieto8"
        },
        {
            "tweet_id": "1520713704169422848",
            "text": "Y llego!!!!!!!\n 1-0 @realracingclub https://t.co/7IfgTEwIDY",
            "created_at": "2022-05-01T10:36:15.000Z",
            "user_id": "604530801",
            "username": "vicentenieto8"
        },
        {
            "tweet_id": "1520709225248350208",
            "text": "El primer gol, de la @GradonaMalditos \ud83d\udc9a\u26bd https://t.co/vFKLNlWRos",
            "created_at": "2022-05-01T10:18:27.000Z",
            "user_id": "604530801",
            "username": "vicentenieto8"
        },
        {
            "tweet_id": "1520473154187149312",
            "text": "Ahora mas que nunca!!\nAnimo @bmSinfin \ud83d\udda4",
            "created_at": "2022-04-30T18:40:23.000Z",
            "user_id": "604530801",
            "username": "vicentenieto8"
        },
        {
            "tweet_id": "1520448572029870081",
            "text": "Nos estamos jugando la vida @bmSinfin \nY moriremos!!! \ud83d\udda4 https://t.co/B47aRSfRNI",
            "created_at": "2022-04-30T17:02:42.000Z",
            "user_id": "604530801",
            "username": "vicentenieto8"
        },
        {
            "tweet_id": "1519626402009694209",
            "text": "@potamitorrc @AitorAlexandre Grande Tomy y grande la abuela!!! \ud83d\udcaa\ud83d\udc9a\u26bd",
            "created_at": "2022-04-28T10:35:42.000Z",
            "user_id": "604530801",
            "username": "vicentenieto8"
        },
        {
            "tweet_id": "1519578159942934528",
            "text": "@potamitorrc @realracingclub @GradonaMalditos @APR_Racing \ud83d\udcaa\ud83d\udcaa\ud83d\udc9a a romperla!!! \u2705\ud83d\udce3\ud83d\udce3\ud83d\udce3\ud83c\udfa4\u26bd",
            "created_at": "2022-04-28T07:24:00.000Z",
            "user_id": "604530801",
            "username": "vicentenieto8"
        },
        {
            "tweet_id": "1518873269868318724",
            "text": "Urgente y necesario. \nEl domingo debe de ser la guinda a unos ultimos dias de una temporada inolvidable y la capital de Cantabria \ud83c\uddf5\ud83c\uddf1 tiene que ser verdiblanca\ud83d\udc9a https://t.co/ZmFJI5m7OC",
            "created_at": "2022-04-26T08:43:01.000Z",
            "user_id": "604530801",
            "username": "vicentenieto8"
        },
        {
            "tweet_id": "1518824084775346176",
            "text": "@potamitorrc @ArceRuiz1975 @GradonaMalditos @realracingclub @APR_Racing A romper esa tarima\ud83c\udfa4\ud83d\udce2 el domingo \u26a1\ud83d\udc9a",
            "created_at": "2022-04-26T05:27:34.000Z",
            "user_id": "604530801",
            "username": "vicentenieto8"
        },
        {
            "tweet_id": "1518677902216380416",
            "text": "Preparados, listos....\n@ArceRuiz1975 si nos lo manda la @GradonaMalditos a obedecer!!\nUn sentimiento, una ilusion @realracingclub \ud83d\udc9a\n@APR_Racing\nEl domingo sera una fiesta el Sardinero \ud83c\udfdf\ufe0f\u26bd\ud83d\udd1d\n#ascenso #esteanosi #Cantabria #Santander https://t.co/cfsXNuy2G4",
            "created_at": "2022-04-25T19:46:42.000Z",
            "user_id": "604530801",
            "username": "vicentenieto8"
        },
        {
            "tweet_id": "1517992403910725634",
            "text": "@caarmenostolaza @antonsetieen7 Animo Anton, grande, muy grande! \ud83d\udc94",
            "created_at": "2022-04-23T22:22:46.000Z",
            "user_id": "604530801",
            "username": "vicentenieto8"
        },
        {
            "tweet_id": "1517946233066864641",
            "text": "Que locura viejo\nAupa @realracingclub \ud83d\udc9a\ud83c\uddf5\ud83c\uddf1 https://t.co/DHLBezSDJc",
            "created_at": "2022-04-23T19:19:18.000Z",
            "user_id": "604530801",
            "username": "vicentenieto8"
        },
        {
            "tweet_id": "1517945772582621184",
            "text": "Puntito a puntito o como la esperanza de un equipo humilde que nunca dejara de creer.\n#aupasinfin \ud83d\udda4\ud83c\uddf5\ud83c\uddf1 https://t.co/fwUnVdg8ie",
            "created_at": "2022-04-23T19:17:28.000Z",
            "user_id": "604530801",
            "username": "vicentenieto8"
        },
        {
            "tweet_id": "1515407243625250819",
            "text": "Otro pasito mas y practicamente definitivo @realracingclub \nOtro nivel la @GradonaMalditos @JJVV86 @APR_Racing \ud83d\udcaa\ud83d\udc9a\nLa piel de gallina!!\n#auparacing\n#esteanosi \u26bd https://t.co/LEGU5RQcPZ",
            "created_at": "2022-04-16T19:10:16.000Z",
            "user_id": "604530801",
            "username": "vicentenieto8"
        },
        {
            "tweet_id": "1513141957475942406",
            "text": "@RicardoRA1913 Animo y pronta recuperacion para tus padres. \u2764\ufe0f",
            "created_at": "2022-04-10T13:08:50.000Z",
            "user_id": "604530801",
            "username": "vicentenieto8"
        },
        {
            "tweet_id": "1508049925686370311",
            "text": "Espectacular el Sardinero \ud83d\udc9a\u26bd\n\u27a1\ufe0f +3 victoria fundamental\n@realracingclub \nMas cerca del ascenso y es que con esta aficion... #esteanosi\n#auparacing \n@GradonaMalditos \n@auparacing1913 \n@APR_Racing https://t.co/EtNBzbZOdT",
            "created_at": "2022-03-27T11:54:55.000Z",
            "user_id": "604530801",
            "username": "vicentenieto8"
        },
        {
            "tweet_id": "1507791782775566337",
            "text": "Partido por todo lo alto @bmpereda y @AialaZarautz \nImportantes los puntos en juego y fantastico ambiente en el graderio \ud83c\uddf5\ud83c\uddf1\ud83e\udd3e\ud83d\udc9b\n#Santander #Cantabria #guerreras #aupapereda https://t.co/ZiZoIhVAmQ",
            "created_at": "2022-03-26T18:49:09.000Z",
            "user_id": "604530801",
            "username": "vicentenieto8"
        },
        {
            "tweet_id": "1504605263487250442",
            "text": "@guiller_ibio @realracingclub \ud83e\udd23\ud83e\udd23\ud83e\udd23\ud83e\udd23 jugon!!!! Y luego hablan de mal de alturas\n#esteanosi \ud83d\udcaa\ud83d\udc9a",
            "created_at": "2022-03-17T23:47:03.000Z",
            "user_id": "604530801",
            "username": "vicentenieto8"
        },
        {
            "tweet_id": "1503068398443450375",
            "text": "Y es que ....\nSois muy grandes!!!\ud83d\udc9a\ud83d\udc9a\ud83d\udc9a\ud83d\udcaa\nVa por vosotros! @GradonaMalditos @APR_Racing @realracingclub \n#santander #cantabria\n#somosdeprimera https://t.co/PL0eknyGAE",
            "created_at": "2022-03-13T18:00:06.000Z",
            "user_id": "604530801",
            "username": "vicentenieto8"
        },
        {
            "tweet_id": "1500195864249348099",
            "text": "Viva el #deporte viva el #balonmano vivan las #guerreras \u2764\ufe0f\ud83c\uddea\ud83c\uddf8\nSantander volcado con la seleccion espanola y demostrando que apostar por el deporte, ademas de mejorar la vida de todos, genera muchos activos para nuestra ciudad #santander https://t.co/bg0H6SCRIM",
            "created_at": "2022-03-05T19:45:40.000Z",
            "user_id": "604530801",
            "username": "vicentenieto8"
        },
        {
            "tweet_id": "1497982238482481160",
            "text": "Este partido quizas se empezo ganando el #tetuan pero los que lo remataron fue la @GradonaMalditos \ud83d\udcaa\ud83d\udcaa\ud83d\udc9a\ud83d\udc9a\n#auparacimg https://t.co/k99RMunENL",
            "created_at": "2022-02-27T17:09:31.000Z",
            "user_id": "604530801",
            "username": "vicentenieto8"
        },
        {
            "tweet_id": "1496567408877879299",
            "text": "@Corocotta68 @realracingclub Gracias a vosotros! \ud83d\udc9a\ud83d\udcaa Anima a seguir dandose contra la pared \ud83e\udd26",
            "created_at": "2022-02-23T19:27:29.000Z",
            "user_id": "604530801",
            "username": "vicentenieto8"
        },
        {
            "tweet_id": "1496493950747779080",
            "text": "@loslocosinfini1 @19racinguista13 @realracingclub Ahi radica el principal problema! Aupa \ud83d\udcaa\ud83d\udc9a",
            "created_at": "2022-02-23T14:35:36.000Z",
            "user_id": "604530801",
            "username": "vicentenieto8"
        },
        {
            "tweet_id": "1496493845294551048",
            "text": "@sufringuista @realracingclub Gracias por vuestro apoyo! \ud83d\udcaa\ud83d\udc9a",
            "created_at": "2022-02-23T14:35:10.000Z",
            "user_id": "604530801",
            "username": "vicentenieto8"
        },
        {
            "tweet_id": "1495382570208485380",
            "text": "Y es que hoy como recuerdo a #NandoYosu no podia ser un domingo cualquiera!\nVictoria importantisimas del @realracingclub y @bmSinfin (mencion especial para un #guerrero @erni_12 )\nFelices \u263a\ufe0f y buen regreso para los aficionados desde Salamanca\nY es que...\n #VivaElDeporte \ud83d\udc9a\ud83d\udda4\ud83c\uddf5\ud83c\uddf1 https://t.co/AU3cz6oFOg",
            "created_at": "2022-02-20T12:59:22.000Z",
            "user_id": "604530801",
            "username": "vicentenieto8"
        },
        {
            "tweet_id": "1494061116560977920",
            "text": "Y es que....\nSoy del @realracingclub \n#auparacing \ud83d\udc9a\ud83d\udcaa\ud83c\uddf5\ud83c\uddf1",
            "created_at": "2022-02-16T21:28:23.000Z",
            "user_id": "604530801",
            "username": "vicentenieto8"
        },
        {
            "tweet_id": "1493309518025011205",
            "text": "Un abrazo a toda la familia @bmSinfin \nLa vida que injusta es a veces \ud83d\udda4 https://t.co/SOHfI9AHw5",
            "created_at": "2022-02-14T19:41:48.000Z",
            "user_id": "604530801",
            "username": "vicentenieto8"
        },
        {
            "tweet_id": "1492917562790887425",
            "text": "@sufringuista Dios mio, esta manana antes del partido he sido conocedor de ello y he estado mas tiempo mirando hacia arriba que al cesped. Manana he hablado con el club, y hare peticion formal de visita a la cubierta y torres de focos, sabremos de primera mano su estado. Gracias\ud83d\udc9a",
            "created_at": "2022-02-13T17:44:18.000Z",
            "user_id": "604530801",
            "username": "vicentenieto8"
        },
        {
            "tweet_id": "1492576417078468611",
            "text": "Despues de tres ataques de ansiedad, dos atragantamientos y un amago de infarto...\n@ADEMARLEON 20\n@bmSinfin            21\nO la historia de cuando @erni_12 se hizo mas grande que la porteria\nSeguimos haciendo camino \ud83c\uddf5\ud83c\uddf1\n#aupasinfin \ud83d\udda4 https://t.co/jMvRt5T4UQ",
            "created_at": "2022-02-12T19:08:43.000Z",
            "user_id": "604530801",
            "username": "vicentenieto8"
        },
        {
            "tweet_id": "1491516621889937414",
            "text": "Enorme esfuerzo para una grata recompensa. Mantenemos viva la ilusion \ud83d\udda4\n@bmSinfin 24\n @BMGranollers 23\n#aupasinfin \ud83c\uddf5\ud83c\uddf1 https://t.co/PlUW4rDllh",
            "created_at": "2022-02-09T20:57:28.000Z",
            "user_id": "604530801",
            "username": "vicentenieto8"
        },
        {
            "tweet_id": "1490301726460719107",
            "text": "A pesar de todas las dificultades del mundo, siempre @bmSinfin \ud83d\udda4\nDos puntos fundamentales e importantisimos \ud83d\udcaa\ud83c\uddf5\ud83c\uddf1 https://t.co/k7HOe5rdNY",
            "created_at": "2022-02-06T12:29:54.000Z",
            "user_id": "604530801",
            "username": "vicentenieto8"
        },
        {
            "tweet_id": "1489262760181460997",
            "text": "https://t.co/Suq6UcbU2G via @ifomo Noticias 24h",
            "created_at": "2022-02-03T15:41:25.000Z",
            "user_id": "604530801",
            "username": "vicentenieto8"
        },
        {
            "tweet_id": "1487113483850338314",
            "text": "No se puede consentir ni un minuto mas que a una instalacion que llevamos domingo tras domingo a nuestras familias y amigos y ante las afirmaciones del responsable de la concejalia de deportes, tildando de\"no segura\" la instalacion no se tomen medidas urgentes.\nEs gravisimo! \ud83e\udd26\ud83d\udc9a https://t.co/uyJrKopuT4",
            "created_at": "2022-01-28T17:20:58.000Z",
            "user_id": "604530801",
            "username": "vicentenieto8"
        },
        {
            "tweet_id": "1483554734963314690",
            "text": "@santandersucio @prcsantander @jmfuentespila @AmparoCoterillo @JesusGoni @prcantabria Creo estais es un error, debierais poder etiquetarme, si no es asi MD porfavor",
            "created_at": "2022-01-18T21:39:46.000Z",
            "user_id": "604530801",
            "username": "vicentenieto8"
        },
        {
            "tweet_id": "1483124358763761670",
            "text": "@OskarGarcia16 Muchas felicidades @OskarGarcia16 \ud83c\udf82\nAbrazo, disfruta de tu dia!",
            "created_at": "2022-01-17T17:09:36.000Z",
            "user_id": "604530801",
            "username": "vicentenieto8"
        },
        {
            "tweet_id": "1482025875277291527",
            "text": "@santandersucio @prcsantander @jmfuentespila @AmparoCoterillo @JesusGoni @prcantabria A vuestra disposicion @santandersucio",
            "created_at": "2022-01-14T16:24:38.000Z",
            "user_id": "604530801",
            "username": "vicentenieto8"
        },
        {
            "tweet_id": "1482025509194190856",
            "text": "@pelicato @prcsantander @MarceDecoscale @jmfuentespila @AmparoCoterillo @JesusGoni @f_martingallego Gracias Mario, tomo nota y lo traslado",
            "created_at": "2022-01-14T16:23:10.000Z",
            "user_id": "604530801",
            "username": "vicentenieto8"
        },
        {
            "tweet_id": "1481007508005269504",
            "text": "@AngelCosmea @prcsantander @RadioFutbolFCF Vamos, pero todo junto a vosotros, es nuestro equipo, nuestro campo, nuestra ciudad! \ud83d\udc9a",
            "created_at": "2022-01-11T20:58:00.000Z",
            "user_id": "604530801",
            "username": "vicentenieto8"
        },
        {
            "tweet_id": "1473614491090923520",
            "text": "A este paso me veo interpretando \"el paciente ingles\" segunda parte...\ud83e\udd26 https://t.co/U4tEjdxJ0T",
            "created_at": "2021-12-22T11:20:47.000Z",
            "user_id": "604530801",
            "username": "vicentenieto8"
        },
        {
            "tweet_id": "1471201819510591493",
            "text": "@LarraldeBrian Animo! \ud83d\udcaa",
            "created_at": "2021-12-15T19:33:42.000Z",
            "user_id": "604530801",
            "username": "vicentenieto8"
        },
        {
            "tweet_id": "1470031863532199945",
            "text": "Lo mas importante y necesario @bmSinfin \nLos dos puntos.\nA seguir creciendo, a seguir trabajando, a seguir creciendo...\nY es que, seguimos creyendo..\n#aupasinfin \ud83d\udda4\n#Cantabria #Santander https://t.co/dSluQOHWEg",
            "created_at": "2021-12-12T14:04:42.000Z",
            "user_id": "604530801",
            "username": "vicentenieto8"
        },
        {
            "tweet_id": "1461021918841163793",
            "text": "Bravo @SDSolares1969 \ud83d\udcaa\ud83d\udcaa\nO la historia de como un sueno puede hacerse realidad!!\nEnhorabuena!! \u2764\ufe0f\nViva el futbol \u26bd\nViva Cantabria \ud83c\uddf5\ud83c\uddf1 https://t.co/VQ3NYhPb6l",
            "created_at": "2021-11-17T17:22:24.000Z",
            "user_id": "604530801",
            "username": "vicentenieto8"
        },
        {
            "tweet_id": "1459602628825042944",
            "text": "Fantastico @bmSinfin \nPasito a pasito haciendo camino!! \ud83d\udc63\ud83d\udc63\ud83d\udc63\ud83d\udcaa\ud83d\udda4\ud83c\uddf5\ud83c\uddf1 https://t.co/KRVMT3jlV9",
            "created_at": "2021-11-13T19:22:39.000Z",
            "user_id": "604530801",
            "username": "vicentenieto8"
        },
        {
            "tweet_id": "1458176096483033099",
            "text": "@jennyferduran23 A todo eso, que comparto, tambien un abrazo largo antes de cerrar los ojitos....",
            "created_at": "2021-11-09T20:54:07.000Z",
            "user_id": "604530801",
            "username": "vicentenieto8"
        },
        {
            "tweet_id": "1457364658218803201",
            "text": "Enhorabuena por el cincuenta cumpleanos 5\ufe0f\u20e30\ufe0f\u20e3\ud83d\udd1d\ud83c\udf82\nAdemas que mejor regalo que una victoria @Independ_RC 31-14 @UribealdeaRugby \n#Santander #Rugby #Cantabria \ud83c\udfc8\ud83c\uddf5\ud83c\uddf1 https://t.co/j4ZGSPWRu8",
            "created_at": "2021-11-07T15:09:45.000Z",
            "user_id": "604530801",
            "username": "vicentenieto8"
        },
        {
            "tweet_id": "1453453300486090759",
            "text": "@Estefania29m Feliz miercoles!!! Me puede decir la marca y grado de proteccion de la crema? \nGracias!!",
            "created_at": "2021-10-27T20:07:25.000Z",
            "user_id": "604530801",
            "username": "vicentenieto8"
        },
        {
            "tweet_id": "1453095695615934467",
            "text": "@grupotecniobras @raulhuerta81 @prcsantander @jmfuentespila @AmparoCoterillo @JesusGoni Es un primer paso, importante la voluntad politica lo primero Luis! Abrazo fuerte",
            "created_at": "2021-10-26T20:26:25.000Z",
            "user_id": "604530801",
            "username": "vicentenieto8"
        }
    ]
}